menglingtool/__init__.py
menglingtool/calendar.py
menglingtool/file.py
menglingtool/goodlib.py
menglingtool/goodlib2.py
menglingtool/hardware.py
menglingtool/model.py
menglingtool/net_tool.py
menglingtool/notice.py
menglingtool/pandas_tool.py
menglingtool/pic.py
menglingtool/process.py
menglingtool/queue.py
menglingtool/rely.py
menglingtool/tcp.py
menglingtool/thread.py
menglingtool/time_tool.py
menglingtool/udp.py
menglingtool/video_tool.py
menglingtool/visualization.py
menglingtool/window_action.py
menglingtool/window_notice.py
menglingtool/word.py
menglingtool/decorates/console.py
menglingtool/decorates/error.py
menglingtool/decorates/retry.py
menglingtool/decorates/select.py
menglingtool/decorates/timeout.py
menglingtool-1.2.4.dist-info/METADATA
menglingtool-1.2.4.dist-info/WHEEL
menglingtool-1.2.4.dist-info/top_level.txt
menglingtool-1.2.4.dist-info/RECORD
