Metadata-Version: 2.1
Name: menglingtool
Version: 1.2.4
Summary: 工业化! yyds
Home-page: https://www.python.org
Author: mengling
Author-email: 1321443305@qq.com
Requires-Python: >3.6
